orcacal/AssistFun.py
orcacal/__init__.py
orcacal/Multiwfn/Multiwfn.exe
orcacal/Multiwfn/Multiwfn_Linux
orcacal/Multiwfn/NAdOs.mwfn
orcacal/Multiwfn/libiomp5md.dll
orcacal/Multiwfn/settings.ini
orcacal/orcacal/__init__.py
orcacal/orcacal/orcacal.py
orcacal-0.0.27.dist-info/LICENSE
orcacal-0.0.27.dist-info/METADATA
orcacal-0.0.27.dist-info/WHEEL
orcacal-0.0.27.dist-info/top_level.txt
orcacal-0.0.27.dist-info/RECORD
