Metadata-Version: 2.1
Name: orcacal
Version: 0.0.27
Summary: test
Home-page: https://github.com/HTY-DBY/orcacal
Author: hty2dby
Author-email: hty@hty.ink
Classifier: Programming Language :: Python :: 3
Classifier: License :: OSI Approved :: MIT License
Classifier: Operating System :: OS Independent
License-File: LICENSE
